DataProTool/DataProTool.py
DataProTool/DataProTool_cn.py
DataProTool/__init__.py
DataProTool-1.2.0.dist-info/LICENSE
DataProTool-1.2.0.dist-info/METADATA
DataProTool-1.2.0.dist-info/WHEEL
DataProTool-1.2.0.dist-info/top_level.txt
DataProTool-1.2.0.dist-info/RECORD
