Metadata-Version: 2.1
Name: DataProTool
Version: 1.2.0
Summary: It is a library that support advance tools in feature engineering.
Home-page: https://github.com/Zhang-Jiexi/DataProTool
Author: Zhang Jiexi
Author-email: zhangjiexi66696@outlook.com
License: MIT License
Classifier: Programming Language :: Python :: 3.9
Classifier: License :: OSI Approved :: MIT License
Classifier: Operating System :: Microsoft
Classifier: Natural Language :: English
Classifier: Natural Language :: Chinese (Simplified)
Classifier: Development Status :: 5 - Production/Stable
Classifier: Intended Audience :: Developers
Classifier: Intended Audience :: Information Technology
Classifier: Topic :: Scientific/Engineering :: Artificial Intelligence
Classifier: Topic :: Scientific/Engineering :: Information Analysis
License-File: LICENSE
Requires-Dist: numpy (>=1.23.3)
Requires-Dist: pandas (>=1.5.0)
Requires-Dist: scikit-learn (>=1.0.2)
Requires-Dist: tqdm (>=4.64.1)
